boxapi/__init__.py
boxapi/box_api_client.py
boxapi/constants.py
boxapi/instagram/__init__.py
boxapi/instagram/instagram_api_client.py
boxapi/instagram/instagram_dm_client.py
boxapi/utils/__init__.py
boxapi/utils/base_url_session.py
boxapi/utils/decorators.py
boxapi-1.0.2.dist-info/LICENSE
boxapi-1.0.2.dist-info/METADATA
boxapi-1.0.2.dist-info/WHEEL
boxapi-1.0.2.dist-info/RECORD
