Metadata-Version: 2.3
Name: boxapi
Version: 1.0.2
Summary: Python client for https://boxapi.ir to crawl and read Instagram data.
License: MIT
Author: Amir Hosein Salimi
Author-email: iamirhoseinslaimi@gmail.com
Requires-Python: >=3.9,<4.0
Classifier: License :: OSI Approved :: MIT License
Classifier: Programming Language :: Python :: 3
Classifier: Programming Language :: Python :: 3.9
Classifier: Programming Language :: Python :: 3.10
Classifier: Programming Language :: Python :: 3.11
Classifier: Programming Language :: Python :: 3.12
Classifier: Programming Language :: Python :: 3.13
Requires-Dist: requests (>=2.32.3,<3.0.0)
Project-URL: Homepage, https://github.com/amirhoseinsalimi/boxapi-python
Project-URL: Repository, https://github.com/amirhoseinsalimi/boxapi-python
